chow_test/__init__.py
chowtest-0.1.4.dist-info/METADATA
chowtest-0.1.4.dist-info/RECORD
chowtest-0.1.4.dist-info/WHEEL
chowtest-0.1.4.dist-info/top_level.txt
