Metadata-Version: 2.1
Name: chowtest
Version: 0.1.4
Summary: Python implementation of the Chow test (1960).
Home-page: https://github.com/David-Woroniuk/chowtest
Author: David Woroniuk
Author-email: david.j.woroniuk@durham.ac.uk
License: MIT License
Platform: UNKNOWN
Requires-Dist: numpy
Requires-Dist: pandas
Requires-Dist: sklearn
Requires-Dist: scipy
